klondike/__init__.py
klondike/aws/__init__.py
klondike/aws/redshift.py
klondike/aws/s3.py
klondike/base/__init__.py
klondike/base/abc_klondike.py
klondike/gcp/__init__.py
klondike/gcp/bigquery.py
klondike/gcp/cloud_storage.py
klondike/postgres/__init__.py
klondike/postgres/postgres.py
klondike/snowflake/__init__.py
klondike/snowflake/snowflake.py
klondike/utilities/__init__.py
klondike/utilities/utilities.py
klondike-0.2.3.dist-info/LICENSE
klondike-0.2.3.dist-info/METADATA
klondike-0.2.3.dist-info/WHEEL
klondike-0.2.3.dist-info/RECORD
